bingsearch/__init__.py
bingsearch/bingsearch.py
python_bingsearch-1.1.0.dist-info/LICENSE
python_bingsearch-1.1.0.dist-info/METADATA
python_bingsearch-1.1.0.dist-info/WHEEL
python_bingsearch-1.1.0.dist-info/entry_points.txt
python_bingsearch-1.1.0.dist-info/top_level.txt
python_bingsearch-1.1.0.dist-info/RECORD
