Metadata-Version: 2.1
Name: python-bingsearch
Version: 1.1.0
Summary: bing Search unofficial API for Python with no external dependencies
Home-page: https://github.com/samsha1971/python-bingsearch
Author: Sam Sha
Author-email: sam_sha@163.com
Maintainer: Sam Sha
Keywords: search-api bing python
Platform: all
Classifier: Development Status :: 5 - Production/Stable
Classifier: Topic :: Utilities
Classifier: License :: OSI Approved :: MIT License
Classifier: Programming Language :: Python :: 2
Classifier: Programming Language :: Python :: 3
License-File: LICENSE
Requires-Dist: requests>=2.32.3
Requires-Dist: beautifulsoup4>=4.12.3
Requires-Dist: lxml>=5.3.0
Requires-Dist: playwright>=1.48.0
